{"Honda": {"Accord": ["Sedan"], "Accord Crosstour": ["SUV"], "CR-V": ["SUV"], "Civic": ["Sedan", "Hatchback", "Coupe"], "Clarity": ["Sedan"], "Element": ["SUV"], "Fit": ["Hatchback"], "HR-V": ["SUV"], "Insight": ["Sedan", "Hatchback"], "Odyssey": ["Minivan"], "Passport": ["SUV"], "Pilot": ["SUV"], "Ridgeline": ["Pickup"], "S2000": ["Convertible"]}, "Chevrolet": {"Astro": ["Van"], "Avalanche 1500": ["SUV"], "Aveo": ["Hatchback"], "Blazer": ["SUV"], "Blazer EV": ["SUV"], "Bolt EUV": ["SUV"], "Bolt EV": ["Hatchback"], "Camaro": ["Coupe", "Convertible"], "Captiva Sport": ["SUV"], "Colorado": ["Pickup"], "Corvette": ["Coupe", "Convertible"], "Cruze": ["Sedan", "Hatchback"], "Equinox": ["SUV"], "Equinox EV": ["SUV"], "Express": ["Van", "Chassis"], "Impala": ["Sedan"], "Malibu": ["Sedan"], "SS": ["Sedan"], "Silverado 1500": ["Pickup"], "Silverado 2500HD": ["Pickup", "Chassis"], "Silverado 3500": ["Pickup"], "Silverado 3500HD": ["Pickup", "Chassis"], "Silverado EV": ["Pickup"], "Sonic": ["Hatchback", "Sedan"], "Spark": ["Hatchback"], "Spark EV": ["Hatchback"], "Suburban": ["SUV"], "Suburban 1500": ["SUV"], "Tahoe": ["SUV"], "TrailBlazer": ["SUV"], "Traverse": ["SUV"], "Trax": ["SUV"], "Volt": ["Sedan"]}, "Kia": {"Cadenza": ["Sedan"], "Carnival": ["Minivan"], "EV6": ["SUV"], "EV9": ["SUV"], "Forte": ["Sedan"], "Forte5": ["Hatchback"], "K4": ["Sedan"], "K5": ["Sedan"], "Niro": ["SUV"], "Niro EV": ["SUV"], "Optima": ["Sedan"], "Rio": ["Hatchback", "Sedan"], "Sedona": ["Minivan"], "Seltos": ["SUV"], "Sorento": ["SUV"], "Soul": ["Wagon"], "Sportage": ["SUV"], "Stinger": ["Sedan"], "Telluride": ["SUV"]}, "Nissan": {"Altima": ["Sedan"], "Ariya": ["SUV"], "Armada": ["SUV"], "Frontier": ["Pickup"], "Juke": ["SUV"], "Kicks": ["SUV"], "Leaf": ["Hatchback"], "Maxima": ["Sedan"], "Murano": ["SUV"], "NV": ["Van"], "NV200": ["Van"], "Pathfinder": ["SUV"], "Quest": ["Minivan"], "Rogue": ["SUV"], "Rogue Sport": ["SUV"], "Sentra": ["Sedan"], "Titan": ["Pickup"], "Titan XD": ["Pickup"], "Versa": ["Sedan", "Hatchback"], "Versa Note": ["Hatchback"], "Xterra": ["SUV"], "Z": ["Coupe", "Convertible"]}, "BMW": {"2 Series": ["Sedan", "Coupe", "Convertible"], "3 Series": ["Sedan", "Convertible", "Hatchback"], "4 Series": ["Sedan", "Coupe", "Convertible"], "5 Series": ["Sedan", "Hatchback"], "6 Series": ["Convertible", "Sedan"], "7 Series": ["Sedan"], "8 Series": ["Coupe", "Sedan", "Convertible"], "M Roadster": ["Convertible"], "M2": ["Coupe"], "M2 CS": ["Coupe"], "M3": ["Sedan", "Convertible"], "M4": ["Convertible"], "M5": ["Sedan", "Wagon"], "M8": ["Sedan", "Convertible"], "X1": ["SUV"], "X2": ["SUV"], "X3": ["SUV"], "X3 M": ["SUV"], "X4": ["SUV"], "X4 M": ["SUV"], "X5": ["SUV"], "X5 M": ["SUV"], "X6": ["SUV"], "X6 M": ["SUV"], "X7": ["SUV"], "XM": ["SUV"], "Z3": ["Convertible"], "Z4": ["Convertible"], "i3": ["Hatchback"], "i4": ["Sedan"], "i5": ["Sedan"], "i7": ["Sedan"], "iX": ["SUV"]}, "Dodge": {"Avenger": ["Sedan"], "Caliber": ["Hatchback"], "Challenger": ["Coupe"], "Charger": ["Sedan", "Coupe"], "Dart": ["Sedan"], "Durango": ["SUV"], "Grand Caravan": ["Minivan"], "Hornet": ["SUV"], "Journey": ["SUV"], "Nitro": ["SUV"], "Ram 2500": ["Pickup"], "Ram 3500": ["Pickup"], "Sprinter": ["Van"], "Viper": ["Convertible"]}, "Ford": {"Bronco": ["SUV"], "Bronco Sport": ["SUV"], "C-Max": ["Minivan"], "Crown Victoria": ["Sedan"], "E-Transit": ["Van"], "EcoSport": ["SUV"], "Econoline": ["Van"], "Edge": ["SUV"], "Escape": ["SUV"], "Expedition": ["SUV"], "Expedition EL": ["SUV"], "Expedition MAX": ["SUV"], "Explorer": ["SUV"], "F-150": ["Pickup"], "F-150 Lightning": ["Pickup"], "F-250": ["Pickup", "Chassis"], "F-350": ["Pickup", "Chassis"], "F-450": ["Pickup"], "Fiesta": ["Sedan", "Hatchback"], "Flex": ["SUV"], "Focus": ["Sedan", "Hatchback"], "Fusion": ["Sedan"], "Maverick": ["Pickup"], "Mustang": ["Coupe", "Convertible"], "Mustang Mach-E": ["SUV"], "Ranger": ["Pickup"], "Taurus": ["Sedan"], "Thunderbird": ["Convertible"], "Transit": ["Van", "Chassis"], "Transit Connect": ["Minivan"]}, "Ram": {"1500": ["Pickup"], "2500": ["Pickup", "Chassis"], "3500": ["Pickup", "Chassis"], "C/V": ["Minivan"], "ProMaster": ["Van"], "ProMaster City": ["Minivan"], "ProMaster EV": ["Van"]}, "GMC": {"Acadia": ["SUV"], "Canyon": ["Pickup"], "Hummer EV": ["SUV", "Pickup"], "Savana": ["Van", "Chassis"], "Sierra 1500": ["Pickup"], "Sierra 2500HD": ["Pickup", "Chassis"], "Sierra 3500HD": ["Pickup", "Chassis"], "Sierra EV": ["Pickup"], "Terrain": ["SUV"], "Yukon": ["SUV"], "Yukon XL": ["SUV"]}, "Audi": {"A3": ["Sedan", "Hatchback", "Convertible"], "A4": ["Sedan", "Wagon", "Convertible"], "A5": ["Hatchback", "Sedan", "Convertible", "Coupe"], "A6": ["Sedan"], "A6 e-tron": ["Hatchback"], "A7": ["Hatchback"], "A8": ["Sedan"], "Allroad": ["Wagon"], "Q3": ["SUV"], "Q5": ["SUV"], "Q6 e-tron": ["SUV"], "Q7": ["SUV"], "Q8": ["SUV"], "R8": ["Convertible", "Coupe"], "RS Q8": ["SUV"], "RS3": ["Sedan"], "RS5": ["Hatchback", "Convertible"], "RS6": ["Wagon"], "RS7": ["Hatchback"], "S3": ["Sedan"], "S4": ["Sedan"], "S5": ["Hatchback", "Coupe", "Sedan", "Convertible"], "S6": ["Sedan"], "S7": ["Hatchback"], "S8": ["Sedan"], "SQ5": ["SUV"], "SQ7": ["SUV"], "SQ8": ["SUV"], "TT": ["Convertible"], "e-tron": ["SUV"], "e-tron GT": ["Sedan"]}, "Buick": {"Cascada": ["Convertible"], "Enclave": ["SUV"], "Encore": ["SUV"], "Encore GX": ["SUV"], "Envision": ["SUV"], "Envista": ["SUV"], "LaCrosse": ["Sedan"], "Lucerne": ["Sedan"], "Regal": ["Hatchback", "Sedan", "Wagon"], "Rendezvous": ["SUV"], "Verano": ["Sedan"]}, "Land Rover": {"Defender": ["SUV"], "Discovery": ["SUV"], "Discovery Sport": ["SUV"], "Range Rover": ["SUV"], "Range Rover Evoque": ["SUV", "Convertible"], "Range Rover Sport": ["SUV"], "Range Rover Velar": ["SUV"]}, "Hyundai": {"Accent": ["Hatchback", "Sedan"], "Azera": ["Sedan"], "Elantra": ["Sedan", "Hatchback"], "Elantra N": ["Sedan"], "Equus": ["Sedan"], "Genesis": ["Sedan"], "Ioniq": ["Hatchback"], "Ioniq 5": ["SUV"], "Ioniq 6": ["Sedan"], "Ioniq 9": ["SUV"], "Kona": ["SUV"], "Palisade": ["SUV"], "Santa Cruz": ["Pickup"], "Santa Fe": ["SUV"], "Santa Fe Sport": ["SUV"], "Santa Fe XL": ["SUV"], "Sonata": ["Sedan"], "Tucson": ["SUV"], "Veloster": ["Hatchback"], "Veloster N": ["Hatchback"], "Venue": ["SUV"]}, "Mercedes-Benz": {"A-Class": ["Sedan"], "AMG GT": ["Coupe", "Convertible"], "B-Class": ["Hatchback"], "C-Class": ["Sedan", "Convertible"], "CL-Class": ["Coupe"], "CLA": ["Sedan"], "CLE": ["Convertible"], "CLK": ["Coupe", "Convertible"], "CLS": ["Sedan"], "E-Class": ["Sedan", "Convertible", "Wagon", "Coupe"], "EQB": ["SUV"], "EQE": ["SUV", "Sedan"], "EQS": ["SUV", "Sedan"], "G-Class": ["SUV"], "GL-Class": ["SUV"], "GLA": ["SUV"], "GLB": ["SUV"], "GLC": ["SUV"], "GLE": ["SUV"], "GLS": ["SUV"], "M-Class": ["SUV"], "Metris": ["Van"], "S-Class": ["Sedan", "Convertible"], "SL-Class": ["Convertible"], "SLC": ["Convertible"], "SLK": ["Convertible"], "Sprinter": ["Van"], "eSprinter": ["Van"]}, "Jeep": {"Cherokee": ["SUV"], "Commander": ["SUV"], "Compass": ["SUV"], "Gladiator": ["Pickup"], "Grand Cherokee": ["SUV"], "Grand Cherokee L": ["SUV"], "Grand Wagoneer": ["SUV"], "Liberty": ["SUV"], "Patriot": ["SUV"], "Renegade": ["SUV"], "Wagoneer": ["SUV"], "Wrangler": ["SUV"]}, "Subaru": {"Ascent": ["SUV"], "BRZ": ["Coupe"], "Crosstrek": ["SUV"], "Forester": ["SUV"], "Impreza": ["Wagon", "Sedan"], "Legacy": ["Sedan"], "Outback": ["Wagon", "SUV"], "Solterra": ["SUV"], "WRX": ["Sedan"]}, "Polestar": {"2": ["Sedan"], "3": ["SUV"]}, "Toyota": {"4Runner": ["SUV"], "Avalon": ["Sedan"], "C-HR": ["SUV"], "Camry": ["Sedan"], "Camry Solara": ["Convertible"], "Corolla": ["Sedan", "Hatchback"], "Corolla Cross": ["SUV"], "Corolla iM": ["Hatchback"], "Crown": ["Sedan"], "Crown Signia": ["SUV"], "FJ Cruiser": ["SUV"], "GR Corolla": ["Hatchback"], "GR Supra": ["Coupe"], "GR86": ["Coupe"], "Grand Highlander": ["SUV"], "Highlander": ["SUV"], "Land Cruiser": ["SUV"], "Matrix": ["Wagon"], "Prius": ["Hatchback"], "Prius Plug-in": ["Hatchback"], "Prius Prime": ["Hatchback"], "Prius c": ["Hatchback"], "RAV4": ["SUV"], "Sequoia": ["SUV"], "Sienna": ["Minivan"], "Tacoma": ["Pickup"], "Tundra": ["Pickup"], "Venza": ["SUV"], "Yaris": ["Hatchback", "Sedan"], "Yaris iA": ["Sedan"], "bZ": ["SUV"], "bZ4X": ["SUV"]}, "Mazda": {"CX-3": ["SUV"], "CX-30": ["SUV"], "CX-5": ["SUV"], "CX-50": ["SUV"], "CX-70": ["SUV"], "CX-9": ["SUV"], "CX-90": ["SUV"], "MAZDASPEED3": ["Hatchback"], "Mazda2": ["Hatchback"], "Mazda3": ["Sedan", "Hatchback"], "Mazda6": ["Sedan"], "Miata": ["Convertible"]}, "Acura": {"ADX": ["SUV"], "ILX": ["Sedan"], "Integra": ["Sedan"], "MDX": ["SUV"], "RDX": ["SUV"], "TL": ["Sedan"], "TLX": ["Sedan"], "TSX": ["Sedan"], "ZDX": ["SUV"]}, "Chrysler": {"200": ["Sedan", "Convertible"], "300": ["Sedan"], "Aspen": ["SUV"], "Crossfire": ["Convertible"], "PT Cruiser": ["Convertible", "Wagon"], "Pacifica": ["Minivan"], "Prowler": ["Convertible"], "Sebring": ["Convertible"], "Town & Country": ["Minivan"], "Voyager": ["Minivan"]}, "Lincoln": {"Aviator": ["SUV"], "Continental": ["Sedan"], "Corsair": ["SUV"], "MKC": ["SUV"], "MKS": ["Sedan"], "MKT": ["SUV"], "MKX": ["SUV"], "MKZ": ["Sedan"], "Nautilus": ["SUV"], "Navigator": ["SUV"], "Navigator L": ["SUV"], "Town Car": ["Sedan"]}, "Volkswagen": {"Arteon": ["Sedan"], "Atlas": ["SUV"], "Beetle": ["Convertible", "Hatchback"], "CC": ["Sedan"], "Eos": ["Convertible"], "Eurovan": ["Van"], "GTI": ["Hatchback"], "Golf": ["Hatchback", "Wagon"], "ID.4": ["SUV"], "ID.Buzz": ["Minivan"], "Jetta": ["Sedan", "Wagon"], "New Beetle": ["Hatchback"], "Passat": ["Sedan"], "Rabbit": ["Hatchback"], "Routan": ["Van"], "Taos": ["SUV"], "Tiguan": ["SUV"], "e-Golf": ["Hatchback"]}, "Porsche": {"718 Boxster": ["Convertible"], "718 Cayman": ["Coupe"], "718 Spyder": ["Convertible"], "911": ["Convertible", "Coupe"], "Boxster": ["Convertible"], "Cayenne": ["SUV"], "Macan": ["SUV"], "Panamera": ["Sedan"], "Taycan": ["Sedan"]}, "Mitsubishi": {"Eclipse": ["Convertible"], "Eclipse Cross": ["SUV"], "Lancer": ["Sedan"], "Lancer Evolution": ["Sedan"], "Mirage": ["Hatchback"], "Mirage G4": ["Sedan"], "Outlander": ["SUV"], "Outlander Sport": ["SUV"]}, "Genesis": {"G70": ["Sedan"], "G80": ["Sedan"], "G90": ["Sedan"], "GV70": ["SUV"], "GV80": ["SUV"]}, "Volvo": {"C30": ["Hatchback"], "C40": ["SUV"], "EX90": ["SUV"], "S40": ["Sedan"], "S60": ["Sedan"], "S90": ["Sedan"], "V60": ["Wagon"], "V90": ["Wagon"], "XC40": ["SUV"], "XC60": ["SUV"], "XC70": ["Wagon"], "XC90": ["SUV"]}, "Infiniti": {"G35": ["Sedan"], "G37": ["Sedan"], "M37": ["Sedan"], "Q50": ["Sedan"], "Q60": ["Coupe"], "QX30": ["SUV"], "QX50": ["SUV"], "QX60": ["SUV"], "QX80": ["SUV"]}, "Lexus": {"CT": ["Hatchback"], "ES": ["Sedan"], "GS": ["Sedan"], "GX": ["SUV"], "IS": ["Sedan"], "LC": ["Convertible"], "LS": ["Sedan"], "LX": ["SUV"], "NX": ["SUV"], "RC": ["Coupe"], "RX": ["SUV"], "RZ": ["SUV"], "SC": ["Convertible"], "TX": ["SUV"]}, "Ferrari": {"296 GTB": ["Coupe"], "296 GTS": ["Convertible"], "360": ["Convertible"], "458": ["Convertible"], "488": ["Coupe", "Convertible"], "812 GTS": ["Convertible"], "California": ["Convertible"], "F430": ["Convertible"], "F8 Spider": ["Convertible"], "Portofino": ["Convertible"], "Portofino M": ["Convertible"], "Roma": ["Convertible"], "SF90": ["Coupe"]}, "Cadillac": {"ATS": ["Coupe", "Sedan"], "CT4": ["Sedan"], "CT5": ["Sedan"], "CT6": ["Sedan"], "CTS": ["Sedan"], "DTS": ["Sedan"], "Escalade": ["SUV"], "Escalade IQ": ["SUV"], "Escalade IQL": ["SUV"], "Lyriq": ["SUV"], "Lyriq-V": ["SUV"], "Optiq": ["SUV"], "SRX": ["SUV"], "XLR": ["Convertible"], "XT4": ["SUV"], "XT5": ["SUV"], "XT6": ["SUV"], "XTS": ["Sedan"]}, "Maserati": {"Ghibli": ["Sedan"], "GranTurismo": ["Convertible", "Coupe"], "Grecale": ["SUV"], "Levante": ["SUV"], "Quattroporte": ["Sedan"]}, "Alfa Romeo": {"4C": ["Convertible"], "Giulia": ["Sedan"], "Stelvio": ["SUV"]}, "Tesla": {"Cybertruck": ["Pickup"], "Model 3": ["Sedan"], "Model S": ["Sedan"], "Model X": ["SUV"], "Model Y": ["SUV"]}, "Mini": {"Cooper": ["Hatchback", "Convertible"], "Cooper Clubman": ["Wagon"], "Cooper Countryman": ["SUV"], "Cooper Paceman": ["Hatchback"], "Cooper Roadster": ["Convertible"]}, "Rivian": {"R1S": ["SUV"], "R1T": ["Pickup"]}, "Jaguar": {"F-Pace": ["SUV"], "F-Type": ["Convertible"], "S-Type": ["Sedan"], "XE": ["Sedan"], "XF": ["Sedan"], "XJ": ["Sedan"], "XK": ["Convertible"]}, "Lotus": {"Emira": ["Coupe"]}, "Aston Martin": {"DB11": ["Convertible"], "DB9": ["Convertible"], "V8 Vantage": ["Coupe", "Convertible"], "Vanquish": ["Convertible"]}, "INEOS": {"Grenadier": ["SUV"]}, "Lucid": {"Air": ["Sedan"]}, "Scion": {"FR-S": ["Coupe"], "iQ": ["Hatchback"], "tC": ["Hatchback"], "xD": ["Hatchback"]}, "Fiat": {"124 Spider": ["Convertible"], "500": ["Hatchback", "Convertible"], "500L": ["Hatchback"], "500X": ["SUV"], "500e": ["Hatchback"]}, "Suzuki": {"SX4": ["Hatchback"]}, "Rolls-Royce": {"Ghost": ["Sedan"], "Phantom": ["Sedan"]}, "Bentley": {"Continental": ["Convertible"], "Flying Spur": ["Sedan"], "Mulsanne": ["Sedan"]}, "Lamborghini": {"Aventador": ["Convertible"], "Gallardo": ["Convertible"], "Huracan": ["Convertible", "Coupe"]}, "Mclaren": {"600LT": ["Coupe"], "720S": ["Convertible"], "750S": ["Convertible"], "Artura": ["Convertible"], "GT": ["Coupe"]}, "Pontiac": {"G6": ["Convertible"], "G8": ["Sedan"], "Grand Prix": ["Sedan"], "Torrent": ["SUV"], "Vibe": ["Wagon"]}, "Mercury": {"Grand Marquis": ["Sedan"], "Mountaineer": ["SUV"]}, "Saab": {"9-3": ["Sedan"]}, "Hummer": {"H3": ["SUV"]}, "Saturn": {"VUE": ["SUV"]}}